{
    "$schema": "https://vega.github.io/schema/vega-lite/v5.json",
    "description": "A histogram showing the distribution of artists' ages in the gallery.",
    "data": {
        "url": "spider_csv/theme_gallery_artist.csv.csv"
    },
    "mark": {
        "type": "bar",
        "tooltip": true
    },
    "encoding": {
        "x": {
            "field": "Age",
            "type": "quantitative",
            "bin": true
        },
        "y": {
            "aggregate": "count",
            "type": "quantitative"
        }
    }
}